MindLake/Cryptor.py
MindLake/DataLake.py
MindLake/KeyHelper.py
MindLake/LICENSE
MindLake/Permission.py
MindLake/README.md
MindLake/Settings.py
MindLake/__init__.py
MindLake/message.py
MindLake/utils.py
mindlake-0.9.0.dist-info/METADATA
mindlake-0.9.0.dist-info/WHEEL
mindlake-0.9.0.dist-info/RECORD
