Metadata-Version: 2.1
Name: MindLake
Version: 0.9.0
Summary: A Python SDK to connect to Mind Lake
Project-URL: Homepage, https://github.com/mind-network/mind-lake-sdk-python
Project-URL: Bug Tracker, https://github.com/mind-network/mind-lake-sdk-python/issues
Author-email: Mind Labs <biz@mindnetwork.xyz>
Keywords: datalake,encryption,web3
Classifier: License :: OSI Approved :: MIT License
Classifier: Operating System :: OS Independent
Classifier: Programming Language :: Python :: 3
Requires-Python: >=3.7
Requires-Dist: colorlog
Requires-Dist: eth-account
Requires-Dist: pynacl
Requires-Dist: web3
